htun_pkg/__init__.py
htun_example_pkg-0.0.1.dist-info/LICENSE
htun_example_pkg-0.0.1.dist-info/METADATA
htun_example_pkg-0.0.1.dist-info/WHEEL
htun_example_pkg-0.0.1.dist-info/top_level.txt
htun_example_pkg-0.0.1.dist-info/RECORD
