Metadata-Version: 2.1
Name: htun-example-pkg
Version: 0.0.1
Summary: testing example python package
Home-page: https://github.com/standingmind/sampleproject
Author: htunlin
Author-email: zhaorenhui81@gmail.com
License: UNKNOWN
Platform: UNKNOWN
Classifier: Programming Language :: Python :: 3
Classifier: License :: OSI Approved :: MIT License
Classifier: Operating System :: OS Independent
Requires-Python: >=3.6
